MANIFEST.in
README.rst
requirements-tests-py2.txt
requirements-tests.txt
setup.py
pony_unitfield/.fields.py.swp
pony_unitfield/__init__.py
pony_unitfield/fields.py
pony_unitfield.egg-info/PKG-INFO
pony_unitfield.egg-info/SOURCES.txt
pony_unitfield.egg-info/dependency_links.txt
pony_unitfield.egg-info/top_level.txt
pony_unitfield/tests/.test_fields.py.swp
pony_unitfield/tests/__init__.py
pony_unitfield/tests/test_fields.py
pony_unitfield/tests/testproject/.models.py.swp
pony_unitfield/tests/testproject/__init__.py
pony_unitfield/tests/testproject/models.py
pony_unitfield/tests/testproject/settings.py
pony_unitfield/tests/testproject/urls.py