Metadata-Version: 1.1
Name: pony-unitfield
Version: 0.2
Summary: Django Field to help metrics handling
Home-page: https://github.com/ZuluPro/pony-unitfield
Author: Anthony Monthe (ZuluPro)
Author-email: anthony.monthe@gmail.com
License: BSD
Keywords: django,models,fields,unit,decimal,float
Platform: UNKNOWN
Classifier: Development Status :: 4 - Beta
Classifier: Environment :: Console
Classifier: Framework :: Django
Classifier: Intended Audience :: Developers
Classifier: License :: OSI Approved :: BSD License
Classifier: Natural Language :: English
Classifier: Operating System :: OS Independent
Classifier: Programming Language :: Python
Classifier: Programming Language :: Python :: 2
Classifier: Programming Language :: Python :: 2.7
Classifier: Programming Language :: Python :: 3
Classifier: Programming Language :: Python :: 3.3
Classifier: Programming Language :: Python :: 3.4
Classifier: Programming Language :: Python :: 3.5
